{"data":{"colour2":"NA","catalogAddDate":1460635320,"colour1":"NA","displayCategories":"Accessories","masterCategory":{"typeName":"Personal Care"},"id":44147,"usage":"Casual","baseColour":"Red","brandName":"Nike Fragrances","season":"Spring","productDescriptors":{"materials_care_desc":{"descriptorType":"materials_care_desc","value":"<p>NA</p>"},"size_fit_desc":{"descriptorType":"size_fit_desc","value":"<p>NA</p>"},"description":{"descriptorType":"description","value":"<p><strong>Style Note <br /></strong> nike fragrances greets you with sporty fragrances that are long lasting and smell great. Put yourself in nike Fragrances's expert care with this deodorant.<br /> <br /><strong> Product Details <br /></strong> Nike Fragrances Extreme is a sporty deodorant for men that comes in an aerosol spray canister <br /> <br /><strong> Caution </strong><br /> Do not use near fire, flame or heat<br /> Avoid spraying in eyes<br /> <br /><strong> Size </strong><br /> 200ml</p>"},"style_note":{"descriptorType":"style_note","value":"<p>NA</p>"}},"articleAttributes":{},"styleOptions":[{"value":"200ML","name":"Size"}],"styleImages":{"default":{"imageURL":"http://assets.myntassets.com/v1/images/style/properties/339319c4068020c232f91bee1072fd76_images.jpg","imageType":"default","resolutions":{"180X240":"http://assets.myntassets.com/h_240,q_95,w_180/v1/images/style/properties/339319c4068020c232f91bee1072fd76_images.jpg","125X161":"http://assets.myntassets.com/h_161,q_95,w_125/v1/images/style/properties/339319c4068020c232f91bee1072fd76_images.jpg"}},"search":{"imageURL":"http://assets.myntassets.com/v1/images/style/properties/339319c4068020c232f91bee1072fd76_images.jpg","imageType":"search","resolutions":{"180X240":"http://assets.myntassets.com/h_240,q_95,w_180/v1/images/style/properties/339319c4068020c232f91bee1072fd76_images.jpg","125X161":"http://assets.myntassets.com/h_161,q_95,w_125/v1/images/style/properties/339319c4068020c232f91bee1072fd76_images.jpg"}}},"productDisplayName":"Nike Fragrances Men Extreme Deo","gender":"Men","subCategory":{"typeName":"Fragrance"},"articleType":{"typeName":"Deodorant"},"ageGroup":"Adults-Men","price":249,"variantName":"Extreme","discountedPrice":249}}